{
  "slug": "terms",
  "path": "/terms",
  "auth": "public",
  "shell": "marketing",
  "browser": "chromium",
  "viewport": {
    "w": 1920,
    "h": 1080,
    "label": "desktop-1920"
  },
  "ok": true,
  "status": 200,
  "error": null,
  "metrics": {
    "url": "http://localhost:3000/terms",
    "title": "Terms of Service | Profytron",
    "viewport": {
      "w": 1920,
      "h": 1080,
      "dpr": 1
    },
    "paints": {
      "first-paint": 1732,
      "first-contentful-paint": 1732
    },
    "lcp": {
      "startTime": 1732,
      "size": 239502,
      "url": null
    },
    "cls": 0.0016768231293792096,
    "inpProxyMs": null,
    "longTaskCount": 2,
    "longTaskTotalMs": 452,
    "tbtProxyMs": 452,
    "navigation": {
      "domContentLoaded": 1613.4000000059605,
      "loadEventEnd": 2307.4000000059605,
      "responseEnd": 399,
      "transferSize": 18386
    },
    "memory": {
      "usedJSHeapSize": 97400000,
      "totalJSHeapSize": 116000000
    },
    "domNodes": 357,
    "js": {
      "scriptCount": 8,
      "scriptTransferKB": 5850
    },
    "network": {
      "apiCount": 0,
      "duplicates": [],
      "sample": []
    },
    "images": {
      "resourceCount": 0,
      "nodes": [
        {
          "src": "http://localhost:3000/_next/image?url=%2Fbrand-mark-tight.png&w=64&q=75",
          "naturalW": 64,
          "naturalH": 65,
          "displayW": 38,
          "displayH": 42,
          "loading": "auto",
          "oversize": false,
          "format": "other"
        },
        {
          "src": "http://localhost:3000/_next/image?url=%2Fbrand-mark-tight.png&w=64&q=75",
          "naturalW": 64,
          "naturalH": 65,
          "displayW": 50,
          "displayH": 54,
          "loading": "auto",
          "oversize": false,
          "format": "other"
        }
      ],
      "oversizeCount": 0,
      "largestTransferKB": 0
    },
    "animation": {
      "avgFps": 47.5,
      "droppedFrames": 4,
      "consoleMetrics": []
    },
    "layoutRuntime": {
      "overflowX": 0,
      "clippedCards": 0,
      "overflowingTables": [],
      "truncatedButtons": 1,
      "overlaps": 0,
      "dialogs": []
    },
    "a11y": {
      "focusableCount": 49,
      "smallTouchTargetCount": 40
    },
    "settled": {
      "main": true,
      "overview": false,
      "ariaBusy": false
    },
    "collectedAt": 4158.600000008941
  },
  "networkLog": {
    "responses": [],
    "failed": 0
  },
  "scroll": null,
  "ts": "2026-07-18T18:41:59.206Z"
}